LICENSE
MANIFEST.in
README.md
setup.py
octopie/__init__.py
octopie/api.py
octopie.egg-info/PKG-INFO
octopie.egg-info/SOURCES.txt
octopie.egg-info/dependency_links.txt
octopie.egg-info/requires.txt
octopie.egg-info/top_level.txt